bigcommerce_toolkit/__init__.py
bigcommerce_toolkit/__main__.py
bigcommerce_toolkit-0.1.14.dist-info/LICENSE.txt
bigcommerce_toolkit-0.1.14.dist-info/METADATA
bigcommerce_toolkit-0.1.14.dist-info/WHEEL
bigcommerce_toolkit-0.1.14.dist-info/entry_points.txt
bigcommerce_toolkit-0.1.14.dist-info/RECORD
