Metadata-Version: 2.1
Name: bigcommerce-toolkit
Version: 0.1.14
Summary: A UNIX-style tool which provides easy access to BigCommerce's API from the command line.
Home-page: https://github.com/TrellisCommerce/bigcommerce-toolkit
Keywords: bigcommerce,api,cli
Author: Joey Hoer
Author-email: me@joeyhoer.com
Requires-Python: >=3.12,<4.0
Classifier: Programming Language :: Python :: 3
Classifier: Programming Language :: Python :: 3.12
Requires-Dist: click (>=8.1,<9.0)
Requires-Dist: requests (>=2.32,<3.0)
Project-URL: Repository, https://github.com/TrellisCommerce/bigcommerce-toolkit
